biasana/__init__.py
biasana/association_analyzer.py
biasana/logit_analyzer.py
biasana/template_manager.py
biasana-0.1.4.dist-info/LICENSE
biasana-0.1.4.dist-info/METADATA
biasana-0.1.4.dist-info/WHEEL
biasana-0.1.4.dist-info/top_level.txt
biasana-0.1.4.dist-info/RECORD
