Metadata-Version: 2.2
Name: biasana
Version: 0.1.4
Summary: A package for analyzing bias in textual data.
Home-page: https://github.com/MostHumble/biasana/
Author-email: sifal klioui <sifalklioui@yahoo.com>
License: Apache 2.0
Project-URL: Homepage, https://github.com/MostHumble/biasana/
Project-URL: Issues, https://github.com/MostHumble/biasana/issues
Classifier: Development Status :: 5 - Production/Stable
Classifier: Intended Audience :: Developers
Classifier: Intended Audience :: Education
Classifier: Intended Audience :: Science/Research
Classifier: License :: OSI Approved :: Apache Software License
Classifier: Operating System :: OS Independent
Classifier: Topic :: Scientific/Engineering :: Artificial Intelligence
Classifier: Programming Language :: Python :: 3.9
Requires-Python: >=3.9
License-File: LICENSE
Requires-Dist: setuptools
Requires-Dist: wheel
Requires-Dist: typing
Requires-Dist: scikit-learn
Requires-Dist: numpy
Requires-Dist: spacy
Requires-Dist: transformers
Requires-Dist: torch
Dynamic: home-page
